updog/Service.py
updog/__init__.py
updog/example.py
updog/logger.py
updog/server.py
updog/service.test.py
updog/updog.py
updog/updog.test.py
updog_py-0.0.2.dist-info/METADATA
updog_py-0.0.2.dist-info/WHEEL
updog_py-0.0.2.dist-info/top_level.txt
updog_py-0.0.2.dist-info/RECORD
