Metadata-Version: 2.1
Name: updog-py
Version: 0.0.2
Requires-Dist: psycopg2
Requires-Dist: requests
Requires-Dist: flask
